reset/timer.v
module timer (CLK, nanos, micros, milis, segs, reset);

//outputs declaration
output reg [9:0] nanos;
output reg [9:0] micros;
output reg [9:0] milis;
output reg [9:0] segs; 

//inputs declaration
input wire CLK;
input wire reset;

always @(posedge CLK or negedge CLK) begin
	if (reset) begin
		nanos <= 0;
		micros <= 0;
		milis <= 0;
		segs <= 0;
	end else begin
		if (nanos < 999) begin
			nanos <= nanos + 1;
		end else begin
			if (micros < 999) begin
				nanos <= 0;
				micros <= micros + 1;
			end else begin
				if (milis < 999) begin 
					micros <= 0;
					milis <= + 1;
				end else begin
					milis <= 0;
					segs <= segs + 1;
				end
			end
		end
	end
end //always

endmodule

reset/Reset_Module.v
`include "timer.v"

module Reset_Module (CLK, reset, cableReset, hardReset, TRANSMIT, ALERT, RECEIVE_DETECT, RECEIVE_BYTE_COUNT, PHY_Stop_Attempting_Reset);

//outputs declaration
output reg [7:0] TRANSMIT; //es un registro de la memoria
output reg [15:0] ALERT;
output reg [7:0] RECEIVE_DETECT;
output reg [7:0] RECEIVE_BYTE_COUNT;
output reg PHY_Stop_Attempting_Reset;

//inputs declaration
input wire CLK;
input wire reset;
input wire cableReset, hardReset;

//variables
wire PHY_reset;
reg [6:0] state;
reg [6:0] nxtState;
integer timeLapse = 10; //por decir algo, algun tiempo
wire [9:0] nanos;
reg nxt_PHY_Stop_Attempting_Reset;
reg timer_Reset;
reg nxt_timer_Reset;

assign PHY_reset = cableReset || hardReset;

// //instancia del timer
timer t1(.CLK(CLK),
			.nanos(nanos), 
			.micros(),
			.milis(),
			.segs(),
			.reset(timer_Reset)
);

//macchine states
localparam IDLE = 								7'b0000001;
localparam PRL_HR_Wait_for_Hard_Reset_Request = 7'b0000010;
localparam PRL_HR_Construct_Message = 			7'b0000100;
localparam PRL_HR_Success = 					7'b0001000;
localparam PRL_HR_Failure = 					7'b0010000;
localparam PRL_HR_Report = 						7'b0100000;
localparam FATAL = 								7'b1000000;

//reset 
always @(posedge CLK) begin 
	if (reset) begin
		state <= IDLE; //initial state
		PHY_Stop_Attempting_Reset <= 0;
		timer_Reset <= 1;
	end else begin
		state <= nxtState;
		PHY_Stop_Attempting_Reset <= nxt_PHY_Stop_Attempting_Reset;
		timer_Reset <= nxt_timer_Reset;
	end //end else
end //always @(posedge CLK)

//STATE MACHINE
always @ (*) begin
	nxtState <= state;
	nxt_PHY_Stop_Attempting_Reset <= PHY_Stop_Attempting_Reset;
	nxt_timer_Reset <= timer_Reset;	
	// TRANSMIT = 0; 
	// ALERT = 0;
	// RECEIVE_DETECT = 0;
	// RECEIVE_BYTE_COUNT = 0;

	case (state)
		//----------FIRST STATE----------
		IDLE: begin
			nxtState <= PRL_HR_Wait_for_Hard_Reset_Request;
		end //IDLE

		//----------SECOND STATE----------
		PRL_HR_Wait_for_Hard_Reset_Request: begin
			nxtState <= PRL_HR_Construct_Message;
		end //PRL_HR_Wait_for_Hard_Reset_Request

		//----------FOURTH STATE----------
		PRL_HR_Construct_Message: begin
			timer_Reset = 0; //Start tHardResetComplete timer
			if (nanos < timeLapse) begin
				if (PHY_reset) begin //Request PHY to send Hard Reset or Cable Reset
					if (cableReset) begin
						TRANSMIT = TRANSMIT | 7'b110; //cable reset
						RECEIVE_BYTE_COUNT <= 1;
					end else begin //si no hay cable reset, 100% hubo hard reset
						TRANSMIT = TRANSMIT | 7'b101; //hard reset
						RECEIVE_BYTE_COUNT <= 0;				
					end
					RECEIVE_DETECT <= 8'b0;
					nxtState <= PRL_HR_Success;	
				end else begin
					nxtState <= PRL_HR_Construct_Message;
				end
			end else begin
				nxtState <= PRL_HR_Failure;
			end
		end //PRL_HR_Construct_Message

		//----------EIGHT STATE----------
		PRL_HR_Success: begin
			timer_Reset = 1; //paro el timer 
			nxtState <= PRL_HR_Report;
		end //PRL_HR_Success

		//----------SIXTEENTHSTATE----------
		PRL_HR_Failure: begin
			timer_Reset = 1; //paro el timer 	
			nxtState <= PRL_HR_Report;
			PHY_Stop_Attempting_Reset <= 1;
		end //PRL_HR_Failure

		//----------THIRTYTWOTH STATE----------
		PRL_HR_Report: begin
			if (cableReset || hardReset) begin 
				ALERT <= ALERT | 16'b1000000; //ALERT.TransmitSuccesful 
			end else begin
				ALERT <= ALERT | 16'b10000; //ALERT.TransmitSOP*MessageFailed
			end
			nxtState <= PRL_HR_Wait_for_Hard_Reset_Request;
		end //PRL_HR_Report
	endcase 	
end //end always @ (*) begin

endmodule

Rx/reloj.v
module relojito(reloj);
	output reloj;
  	reg reloj;

  	initial reloj = 0;
	
  	always
   	#1 reloj = ~reloj;
endmodule

reset/probador_reset.v
`include "reloj.v"

module probador_reset(CLK, reset, cableReset, hardReset, TRANSMIT, ALERT, RECEIVE_DETECT, RECEIVE_BYTE_COUNT, PHY_Stop_Attempting_Reset);
	//inputs
	input wire [7:0] TRANSMIT; //es un registro de la memoria
	input wire [15:0] ALERT;
	input wire [7:0] RECEIVE_DETECT;
	input wire [7:0] RECEIVE_BYTE_COUNT;
	input wire PHY_Stop_Attempting_Reset;

	//clock
	//wire CLK;
	output wire CLK;

	//outputs
	output reg reset; 
	output reg cableReset;
	output reg hardReset;

	relojito c1(CLK); //instancia del relojito

	initial begin
		$dumpfile("reset_output.vcd"); //genera el archivo .vcd
	  	$dumpvars;

		reset = 1; //reset puesto
		cableReset = 0; 
		hardReset = 0; 

		#2 reset = 0;
		
		#20 cableReset <= 1;

		#10 $finish;
	end
endmodule

reset/test_bench_reset.v
`include "probador_reset.v"
`include "Reset_Module.v"

module test_bench_reset;

	//cables de comunicacion entre modulos
	wire clock;
	wire reset;
	wire phy_ack;
	wire cableR;
	wire hardR;
	wire [7:0] TRANS;
	wire [15:0] Alert;
	wire [7:0] REC_DET;
	wire [7:0] REC_B_COUNT;
	wire stop;

	//instancia del probador
	probador_reset p_reset(.CLK(clock),
					.reset(reset),
					.cableReset(cableR),
					.hardReset(hardR),
					.TRANSMIT(TRANS),
					.ALERT(Alert),
					.RECEIVE_DETECT(REC_DET),
					.RECEIVE_BYTE_COUNT(REC_B_COUNT),
					.PHY_Stop_Attempting_Reset(stop)
	);

	//instancia del registro
	Reset_Module maquinita_reset (.CLK(clock),
					.reset(reset),
					.cableReset(cableR),
					.hardReset(hardR),
					.TRANSMIT(TRANS),
					.ALERT(Alert),
					.RECEIVE_DETECT(REC_DET),
					.RECEIVE_BYTE_COUNT(REC_B_COUNT),
					.PHY_Stop_Attempting_Reset(stop)
	);
endmodule

reset/reset_output.vcd
$date
	Thu Jun 22 20:37:27 2017
$end
$version
	Icarus Verilog
$end
$timescale
	1s
$end
$scope module test_bench_reset $end
$var wire 16 ! Alert [15:0] $end
$var wire 8 " REC_B_COUNT [7:0] $end
$var wire 8 # REC_DET [7:0] $end
$var wire 8 $ TRANS [7:0] $end
$var wire 1 % cableR $end
$var wire 1 & clock $end
$var wire 1 ' hardR $end
$var wire 1 ( reset $end
$var wire 1 ) stop $end
$scope module p_reset $end
$var wire 16 * ALERT [15:0] $end
$var wire 1 & CLK $end
$var wire 1 ) PHY_Stop_Attempting_Reset $end
$var wire 8 + RECEIVE_BYTE_COUNT [7:0] $end
$var wire 8 , RECEIVE_DETECT [7:0] $end
$var wire 8 - TRANSMIT [7:0] $end
$var reg 1 . cableReset $end
$var reg 1 / hardReset $end
$var reg 1 0 reset $end
$scope module c1 $end
$var reg 1 1 reloj $end
$upscope $end
$upscope $end
$scope module maquinita_reset $end
$var wire 1 & CLK $end
$var wire 1 2 PHY_reset $end
$var wire 1 % cableReset $end
$var wire 1 ' hardReset $end
$var wire 10 3 nanos [9:0] $end
$var wire 1 ( reset $end
$var reg 16 4 ALERT [15:0] $end
$var reg 1 5 PHY_Stop_Attempting_Reset $end
$var reg 8 6 RECEIVE_BYTE_COUNT [7:0] $end
$var reg 8 7 RECEIVE_DETECT [7:0] $end
$var reg 8 8 TRANSMIT [7:0] $end
$var reg 7 9 nxtState [6:0] $end
$var reg 1 : nxt_PHY_Stop_Attempting_Reset $end
$var reg 1 ; nxt_timer_Reset $end
$var reg 7 < state [6:0] $end
$var integer 32 = timeLapse [31:0] $end
$var reg 1 > timer_Reset $end
$scope module t1 $end
$var wire 1 & CLK $end
$var wire 1 ? reset $end
$var reg 10 @ micros [9:0] $end
$var reg 10 A milis [9:0] $end
$var reg 10 B nanos [9:0] $end
$var reg 10 C segs [9:0] $end
$upscope $end
$upscope $end
$upscope $end
$enddefinitions $end
#0
$dumpvars
bx C
bx B
bx A
bx @
x?
x>
b1010 =
bx <
x;
x:
bx 9
bx 8
bx 7
bx 6
x5
bx 4
bx 3
02
01
10
0/
0.
bx -
bx ,
bx +
bx *
x)
1(
0'
0&
0%
bx $
bx #
bx "
bx !
$end
#1
1;
0:
b10 9
b0 A
1>
1?
05
0)
b1 <
11
1&
#2
b10 9
b0 C
b0 @
b0 B
b0 3
01
0&
00
0(
#3
b100 9
b10 <
11
1&
#4
01
0&
#5
0>
0?
b100 <
11
1&
#6
0;
b1 B
b1 3
01
0&
#7
b10 B
b10 3
11
1&
#8
b11 B
b11 3
01
0&
#9
b100 B
b100 3
11
1&
#10
b101 B
b101 3
01
0&
#11
b110 B
b110 3
11
1&
#12
b111 B
b111 3
01
0&
#13
b1000 B
b1000 3
11
1&
#14
b1001 B
b1001 3
01
0&
#15
b10000 9
b1010 B
b1010 3
11
1&
#16
b10000 9
b1011 B
b1011 3
01
0&
#17
1;
1:
15
1)
b100000 9
1>
1?
b1100 B
b1100 3
b10000 <
11
1&
#18
b100000 9
b0 B
b0 3
01
0&
#19
b10 9
bx1xxxx 4
bx1xxxx !
bx1xxxx *
b100000 <
11
1&
#20
01
0&
#21
b100 9
b10 <
11
1&
#22
b100 9
12
1.
1%
01
0&
#23
b1000 9
b0 7
b0 #
b0 ,
b1 6
b1 "
b1 +
bx11x 8
bx11x $
bx11x -
0>
0?
b100 <
11
1&
#24
0;
b1000 9
b1 B
b1 3
01
0&
#25
b100000 9
1>
1?
b10 B
b10 3
b1000 <
11
1&
#26
1;
b100000 9
b0 B
b0 3
01
0&
#27
b10 9
bx1x1xxxx 4
bx1x1xxxx !
bx1x1xxxx *
b100000 <
11
1&
#28
01
0&
#29
b100 9
b10 <
11
1&
#30
01
0&
#31
b1000 9
0>
0?
b100 <
11
1&
#32
0;
b1000 9
b1 B
b1 3
01
0&
