Rx/Rx_Module.v
module Rx_Module (CLK, reset, Start, iRX_BUF_FRAME_TYPE, iALERT, iRECEIVE_DETECT, iRECEIVE_BYTE_COUNT, 
					Tx_State_Machine_ACTIVE, Unexpected_GoodCRC, CC_Busy, CC_IDLE, Data_In, oALERT, 
					oRECEIVE_BYTE_COUNT, oGoodCRC_to_PHY, oDIR_WRITE, oDATA_to_Buffer);

//inputs declaration
input wire CC_Busy, CC_IDLE;
input wire CLK;
input wire [7:0] Data_In;
input wire [15:0] iALERT; //B3 Hard Reset 
input wire [7:0] iRECEIVE_BYTE_COUNT;
input wire [7:0] iRECEIVE_DETECT;
input wire [7:0] iRX_BUF_FRAME_TYPE; //B2..0   110b: Received Cable Reset
input wire reset;
input wire Start;
input wire Tx_State_Machine_ACTIVE;
input wire Unexpected_GoodCRC;

//outputs declaration
output reg [15:0] oALERT;
output reg [7:0] oDATA_to_Buffer;
output reg [7:0] oDIR_WRITE;
output reg oGoodCRC_to_PHY;
output reg [7:0] oRECEIVE_BYTE_COUNT;

//variables
reg [15:0] nxt_oALERT;
reg [7:0] nxt_oDATA_to_Buffer;
reg [7:0] nxt_oDIR_WRITE;
reg nxt_oGoodCRC_to_PHY;
reg [7:0] nxt_oRECEIVE_BYTE_COUNT;
reg [5:0] nxt_State;
wire PHY_Reset;
reg [5:0] state;

assign PHY_Reset = (iRX_BUF_FRAME_TYPE[2:0] == 3'b110) || (iALERT[3] == 1);

//macchine states
localparam IDLE = 6'b000001;
localparam PRL_Rx_Wait_for_PHY_message = 6'b000010;
localparam PRL_Rx_Message_Discard = 6'b000100;
localparam PRL_RX_Send_GoodCRC = 6'b001000;
localparam PRL_RX_Report_SOP = 6'b010000;
 
parameter max_iRECEIVE_BYTE_COUNT = 31; 
		

//reset 
always @(posedge CLK) begin 
	if (~reset) begin
		state <= IDLE; //initial state
		oDIR_WRITE <= 8'b0;
		oALERT <= 16'b0;
		oRECEIVE_BYTE_COUNT <= 0;
		oGoodCRC_to_PHY <= 0;
		oDATA_to_Buffer <= 8'b0;
	end else begin
		state <= nxt_State;
		oDIR_WRITE <= nxt_oDIR_WRITE;
		oALERT <= nxt_oALERT;
		oRECEIVE_BYTE_COUNT <= nxt_oRECEIVE_BYTE_COUNT;
		oGoodCRC_to_PHY <= nxt_oGoodCRC_to_PHY;
		oDATA_to_Buffer <= nxt_oDATA_to_Buffer;
	end //end else
end //always @(posedge CLK)


//STATE MACHINE
always @ (*) begin
	nxt_State <= state;
	nxt_oGoodCRC_to_PHY <= oGoodCRC_to_PHY;
	nxt_oDIR_WRITE <= oDIR_WRITE;
	nxt_oALERT <= oALERT;
	nxt_oRECEIVE_BYTE_COUNT <= oRECEIVE_BYTE_COUNT;
	nxt_oGoodCRC_to_PHY <= oGoodCRC_to_PHY;
	nxt_oDATA_to_Buffer <= oDATA_to_Buffer;

	case (state)
		//----------FIRST STATE----------
		IDLE: begin
			//logica de proximo estado
			if (!PHY_Reset && !Start) begin //solo en caso de recibir un hard/cable reset o start se pasa de estado
				nxt_State <= IDLE; 
			end else begin
				nxt_State <= PRL_Rx_Wait_for_PHY_message;
			end
		end //IDLE

		//----------SECOND STATE----------
		PRL_Rx_Wait_for_PHY_message: begin
			//logica de proximo estado
			if (iALERT[10]) begin //si hay buffer overflow, osea el buffer esta lleno
				nxt_State <= PRL_Rx_Wait_for_PHY_message; //esperamo a que el buffer se desocupe
			end else begin
				if (iRECEIVE_DETECT & 8'b1) begin //se detecta que hay un mensaje o un dato 
					nxt_State <= PRL_Rx_Message_Discard;
				end else begin
					nxt_State <= IDLE; //si no recibe mensaje entonces se va a IDLE
				end
			end
		end //PRL_Rx_Wait_for_PHY_message

		//----------FOURTH STATE----------
		PRL_Rx_Message_Discard: begin
			//logica de salida
			if (Tx_State_Machine_ACTIVE) begin //si la maquina de Tx esta activa se descarta el mensaje
				nxt_oALERT <= oALERT | 16'b100000; //bandera que indica que se descato el mensaje ALERT B5
				nxt_oRECEIVE_BYTE_COUNT <= 0; //se pone el BYTE_COUNT en 0 xq se descarto el mensaje
			end else begin
				nxt_oALERT <= oALERT;
			end

			//logica de proximo estado
			if (Unexpected_GoodCRC) begin //dependiendo del CRC se pasa al repor o a enviar un GoodCRC
				nxt_State <= PRL_RX_Report_SOP;
			end else begin
				nxt_State <= PRL_RX_Send_GoodCRC;
			end
		end //PRL_Rx_Message_Discard

		//----------EIGTH STATE----------
		PRL_RX_Send_GoodCRC: begin
			//logica de salida
			nxt_oGoodCRC_to_PHY <= 1; //se notifica al PHY que hubo un goodCRC

			//logica de proximo estado
			//si el CC esta ocupado o en IDLE se va a WAIT
			//si el Tx esta acitca se va a wait xq se descarto el mensaje
			if (CC_Busy || CC_IDLE || Tx_State_Machine_ACTIVE) begin
				nxt_State <= PRL_Rx_Wait_for_PHY_message;	
			end else begin //means goodCRC transmission complete
				nxt_State <= PRL_RX_Report_SOP;	
			end
		end //PRL_RX_Send_GoodCRC

		//----------SIXTEENTH STATE----------
		PRL_RX_Report_SOP: begin
			//logica de salida
			//update RECEIVE BUFFER
			nxt_oDATA_to_Buffer <= Data_In; //se copia el dato que va a ser transmitido a la salida

			//se calcula la direccion en el Rx_BUFFER donde se va a guardar el mensaje
			//a partir del BYTE_COUNT
			nxt_oDIR_WRITE <= iRECEIVE_BYTE_COUNT + 8'h31; //en h31 empieza el frame_type

			nxt_oRECEIVE_BYTE_COUNT <= iRECEIVE_BYTE_COUNT + 1; //se notifica que el BUFFER tiene 1 byte mas

			//BYTE_COUNT (1 Byte Frame, 2 Bytes Header, 28 Bytes Datos)
			if (oRECEIVE_BYTE_COUNT == 31) begin //si el BYTE_COUNT llega a 31, el Rx_BUFFER esta lleno
				nxt_oALERT <= oALERT | 16'b10000000000; //bandera de Overflow
			end else begin
				nxt_oALERT <= oALERT & 16'b1111101111111111; //se asegura que la bandera de overflow este en 0
			end

			nxt_oALERT <= oALERT | 16'b000100; //se notifica que el Rx_BUFFER cambio

			//logica de proximo estado
			nxt_State <= PRL_Rx_Wait_for_PHY_message;
		end //PRL_RX_Report_SOP

	endcase 	
end //end always @ (*) begin

endmodule

Rx/reloj.v
module relojito(reloj);
	output reloj;
  	reg reloj;

  	initial reloj = 0;
	
  	always
   	#1 reloj = ~reloj;
endmodule

Rx/probador_Rx.v
`include "reloj.v"

module probador_Rx(CLK, reset, Start, iRX_BUF_FRAME_TYPE, iALERT, iRECEIVE_DETECT, iRECEIVE_BYTE_COUNT, Tx_State_Machine_ACTIVE, Unexpected_GoodCRC, 
					CC_Busy, CC_IDLE, Data_In, oALERT, oRECEIVE_BYTE_COUNT, oGoodCRC_to_PHY, oDIR_WRITE, oDATA_to_Buffer);

	//outputs declaration
	input wire [15:0] oALERT;
	input wire [7:0] oDATA_to_Buffer;
	input wire [7:0] oDIR_WRITE;
	input wire [7:0] oRECEIVE_BYTE_COUNT;
	input wire oGoodCRC_to_PHY;

	//inputs declaration
	output wire CLK;
	output reg reset;
	output reg Start;
	output reg [7:0] iRX_BUF_FRAME_TYPE; //B2..0   110b: Received Cable Reset
	output reg [15:0] iALERT; //B3 Hard Reset 
	output reg [7:0] iRECEIVE_DETECT;
	output reg [7:0] iRECEIVE_BYTE_COUNT;
	output reg Tx_State_Machine_ACTIVE;
	output reg Unexpected_GoodCRC;
	output reg CC_Busy, CC_IDLE;
	output reg [7:0] Data_In;

	relojito c1(CLK); //instancia del relojito

	initial begin
		$dumpfile("Rx_output.vcd"); //genera el archivo .vcd
	  	$dumpvars;

		reset = 0; //reset puesto
		Start = 1;
		CC_Busy = 0;
		CC_IDLE = 0;
		Unexpected_GoodCRC = 0;
		Data_In = 8'b10011001;
		Tx_State_Machine_ACTIVE = 0;
		iRX_BUF_FRAME_TYPE = 8'b0;
		iALERT = 16'b00000000000;
		iRECEIVE_DETECT = 8'b1;
		iRECEIVE_BYTE_COUNT = 8'b0101;

		#4 reset = 1;
		

		#20 $finish;
	end
endmodule

Rx/test_bench_Rx.v
`include "probador_Rx.v"
`include "Rx_Module.v"

module test_bench_Rxt;

	//cables de comunicacion entre modulos
	wire clock;
	wire reset;
	wire start;
	wire [7:0] RX_BUF_FRAME_TYPE; //B2..0   110b: Received Cable Reset
	wire [15:0] ALERT; //B3 Hard Reset 
	wire [7:0] RECEIVE_DETECT;
	wire [7:0] RECEIVE_BYTE_COUNT;
	wire tx_State_Machine_ACTIVE;
	wire unexpected_GoodCRC;
	wire cC_Busy, cC_IDLE;
	wire [7:0] data_In;

	wire [15:0] ALERTo;
	wire [7:0] RECEIVE_BYTE_COUNTo;
	wire GoodCRC_to_PHYo;
	wire [7:0] DIR_WRITEo;
	wire [7:0] DATA_to_Buffero;
	

	//instancia del probador
	probador_Rx p_Rx(.CLK(clock),
					.reset(reset),
					.Start(start),
					.iRX_BUF_FRAME_TYPE(RX_BUF_FRAME_TYPE),
					.iALERT(ALERT),
					.iRECEIVE_DETECT(RECEIVE_DETECT),
					.iRECEIVE_BYTE_COUNT(RECEIVE_BYTE_COUNT),
					.Tx_State_Machine_ACTIVE(tx_State_Machine_ACTIVE),
					.Unexpected_GoodCRC(unexpected_GoodCRC),
					.CC_Busy(cC_Busy),
					.CC_IDLE(cC_IDLE),
					.Data_In(data_In),
					.oALERT(ALERTo),
					.oRECEIVE_BYTE_COUNT(RECEIVE_BYTE_COUNTo),
					.oGoodCRC_to_PHY(GoodCRC_to_PHYo),
					.oDIR_WRITE(DIR_WRITEo),
					.oDATA_to_Buffer(DATA_to_Buffero)
	);

	//instancia del registro
	Rx_Module maquinita_Rx (.CLK(clock),
					.reset(reset),
					.Start(start),
					.iRX_BUF_FRAME_TYPE(RX_BUF_FRAME_TYPE),
					.iALERT(ALERT),
					.iRECEIVE_DETECT(RECEIVE_DETECT),
					.iRECEIVE_BYTE_COUNT(RECEIVE_BYTE_COUNT),
					.Tx_State_Machine_ACTIVE(tx_State_Machine_ACTIVE),
					.Unexpected_GoodCRC(unexpected_GoodCRC),
					.CC_Busy(cC_Busy),
					.CC_IDLE(cC_IDLE),
					.Data_In(data_In),
					.oALERT(ALERTo),
					.oRECEIVE_BYTE_COUNT(RECEIVE_BYTE_COUNTo),
					.oGoodCRC_to_PHY(GoodCRC_to_PHYo),
					.oDIR_WRITE(DIR_WRITEo),
					.oDATA_to_Buffer(DATA_to_Buffero)
	);

endmodule

Rx/Rx_output.vcd
$date
	Fri Jun 23 04:09:54 2017
$end
$version
	Icarus Verilog
$end
$timescale
	1s
$end
$scope module test_bench_Rxt $end
$var wire 16 ! ALERT [15:0] $end
$var wire 16 " ALERTo [15:0] $end
$var wire 8 # DATA_to_Buffero [7:0] $end
$var wire 8 $ DIR_WRITEo [7:0] $end
$var wire 1 % GoodCRC_to_PHYo $end
$var wire 8 & RECEIVE_BYTE_COUNT [7:0] $end
$var wire 8 ' RECEIVE_BYTE_COUNTo [7:0] $end
$var wire 8 ( RECEIVE_DETECT [7:0] $end
$var wire 8 ) RX_BUF_FRAME_TYPE [7:0] $end
$var wire 1 * cC_Busy $end
$var wire 1 + cC_IDLE $end
$var wire 1 , clock $end
$var wire 8 - data_In [7:0] $end
$var wire 1 . reset $end
$var wire 1 / start $end
$var wire 1 0 tx_State_Machine_ACTIVE $end
$var wire 1 1 unexpected_GoodCRC $end
$scope module p_Rx $end
$var wire 1 , CLK $end
$var wire 16 2 oALERT [15:0] $end
$var wire 8 3 oDATA_to_Buffer [7:0] $end
$var wire 8 4 oDIR_WRITE [7:0] $end
$var wire 1 % oGoodCRC_to_PHY $end
$var wire 8 5 oRECEIVE_BYTE_COUNT [7:0] $end
$var reg 1 6 CC_Busy $end
$var reg 1 7 CC_IDLE $end
$var reg 8 8 Data_In [7:0] $end
$var reg 1 9 Start $end
$var reg 1 : Tx_State_Machine_ACTIVE $end
$var reg 1 ; Unexpected_GoodCRC $end
$var reg 16 < iALERT [15:0] $end
$var reg 8 = iRECEIVE_BYTE_COUNT [7:0] $end
$var reg 8 > iRECEIVE_DETECT [7:0] $end
$var reg 8 ? iRX_BUF_FRAME_TYPE [7:0] $end
$var reg 1 @ reset $end
$scope module c1 $end
$var reg 1 A reloj $end
$upscope $end
$upscope $end
$scope module maquinita_Rx $end
$var wire 1 * CC_Busy $end
$var wire 1 + CC_IDLE $end
$var wire 1 , CLK $end
$var wire 8 B Data_In [7:0] $end
$var wire 1 C PHY_Reset $end
$var wire 1 / Start $end
$var wire 1 0 Tx_State_Machine_ACTIVE $end
$var wire 1 1 Unexpected_GoodCRC $end
$var wire 16 D iALERT [15:0] $end
$var wire 8 E iRECEIVE_BYTE_COUNT [7:0] $end
$var wire 8 F iRECEIVE_DETECT [7:0] $end
$var wire 8 G iRX_BUF_FRAME_TYPE [7:0] $end
$var wire 1 . reset $end
$var reg 6 H nxt_State [5:0] $end
$var reg 16 I nxt_oALERT [15:0] $end
$var reg 8 J nxt_oDATA_to_Buffer [7:0] $end
$var reg 8 K nxt_oDIR_WRITE [7:0] $end
$var reg 1 L nxt_oGoodCRC_to_PHY $end
$var reg 8 M nxt_oRECEIVE_BYTE_COUNT [7:0] $end
$var reg 16 N oALERT [15:0] $end
$var reg 8 O oDATA_to_Buffer [7:0] $end
$var reg 8 P oDIR_WRITE [7:0] $end
$var reg 1 Q oGoodCRC_to_PHY $end
$var reg 8 R oRECEIVE_BYTE_COUNT [7:0] $end
$var reg 6 S state [5:0] $end
$upscope $end
$upscope $end
$enddefinitions $end
#0
$dumpvars
bx S
bx R
xQ
bx P
bx O
bx N
bx M
xL
bx K
bx J
bx I
bx H
b110 G
b1 F
b101 E
b0 D
1C
b10011001 B
0A
0@
b110 ?
b1 >
b101 =
b0 <
0;
0:
19
b10011001 8
07
06
bx 5
bx 4
bx 3
bx 2
01
00
1/
0.
b10011001 -
0,
0+
0*
b110 )
b1 (
bx '
b101 &
x%
bx $
bx #
bx "
b0 !
$end
#1
b0 J
b0 M
b0 I
b0 K
0L
b10 H
b0 O
b0 #
b0 3
0Q
0%
b0 R
b0 '
b0 5
b0 N
b0 "
b0 2
b0 P
b0 $
b0 4
b1 S
1A
1,
#2
0A
0,
#3
1A
1,
#4
0A
0,
1@
1.
#5
b100 H
b10 S
1A
1,
#6
0A
0,
#7
b1000 H
b100 S
1A
1,
#8
0A
0,
#9
b10000 H
1L
b1000 S
1A
1,
#10
0A
0,
#11
b10 H
b100 I
b110 M
b110110 K
b10011001 J
1Q
1%
b10000 S
1A
1,
#12
0A
0,
#13
b100 H
b10011001 O
b10011001 #
b10011001 3
b110 R
b110 '
b110 5
b100 N
b100 "
b100 2
b110110 P
b110110 $
b110110 4
b10 S
1A
1,
#14
0A
0,
#15
b1000 H
b100 S
1A
1,
#16
0A
0,
#17
b10000 H
b1000 S
1A
1,
#18
0A
0,
#19
b10 H
b10000 S
1A
1,
#20
0A
0,
#21
b100 H
b10 S
1A
1,
#22
0A
0,
#23
b1000 H
b100 S
1A
1,
#24
0A
0,
